{"en_appendix_appendix-a.md":"DFpHYcru","en_appendix_appendix-b.md":"C9dmpXaO","en_appendix_appendix-c.md":"QKXZEzcl","en_appendix_appendix-d.md":"CbKPC5P4","en_appendix_appendix-e.md":"ud35_X2i","en_chapter1.md":"B3te0_yn","en_chapter10.md":"hA03Y1mF","en_chapter11.md":"bk7BTPVc","en_chapter12.md":"Ch9ygppr","en_chapter13.md":"CQWu8Wud","en_chapter14.md":"YDbKKdDD","en_chapter15.md":"D1MnkVRC","en_chapter16.md":"BUZNrHfr","en_chapter17.md":"CxzNMNYg","en_chapter18.md":"AFfOn2dv","en_chapter19.md":"Bm4O7UfH","en_chapter2.md":"CFJFadut","en_chapter20.md":"DFNHLeTb","en_chapter3.md":"BojqYg0F","en_chapter4.md":"BexRR88j","en_chapter5.md":"DGMhTw2m","en_chapter6.md":"CKws67bc","en_chapter7.md":"DLq3kE-d","en_chapter8.md":"CnFojRar","en_chapter9.md":"D2zsxL58","en_index.md":"CbQADeQZ","en_part1-cognition_chapter1.md":"D-mz2InI","en_part1-cognition_chapter2.md":"BeE_DK1Y","en_part1-cognition_chapter3.md":"Cib8XDqy","en_part2-fundamentals_chapter4.md":"BbCXzyF1","en_part2-fundamentals_chapter5.md":"DJYX1ve6","en_part2-fundamentals_chapter6.md":"2z62eAxC","en_part2-fundamentals_chapter7.md":"BZ3PLwPp","en_part3-practice_chapter10.md":"BKZnd3D4","en_part3-practice_chapter11.md":"TDOr-ooL","en_part3-practice_chapter12.md":"g04x2wCF","en_part3-practice_chapter8.md":"Bsq7ViHv","en_part3-practice_chapter9.md":"CIDl65W4","en_part4-advanced_chapter13.md":"DR44bskT","en_part4-advanced_chapter14.md":"BMZt9tjA","en_part4-advanced_chapter15.md":"C95LUocu","en_part5-career_chapter16.md":"Cj1kv0jC","en_part5-career_chapter17.md":"DHswtHNM","en_part5-career_chapter18.md":"C0WTwdG-","en_part5-career_chapter19.md":"u7kPEqrR","en_part5-career_chapter20.md":"BpLxAxaO","ja_appendix_appendix-a.md":"Bo6yLeTE","ja_appendix_appendix-b.md":"DaS63iRr","ja_appendix_appendix-c.md":"CK5iVjXg","ja_appendix_appendix-d.md":"GEBRK2SA","ja_appendix_appendix-e.md":"Dvr6yIes","ja_chapter1.md":"DedtiMq_","ja_chapter10.md":"Cd1jmqQM","ja_chapter11.md":"CXxr4hrz","ja_chapter12.md":"Bb6UYJC-","ja_chapter13.md":"DnSNT0yv","ja_chapter14.md":"DJFwpscJ","ja_chapter15.md":"BILuLhag","ja_chapter16.md":"ByAhMpWw","ja_chapter17.md":"oMN0Nanq","ja_chapter18.md":"DSWg4qIs","ja_chapter19.md":"wxFhfUtW","ja_chapter2.md":"n5c8BlwB","ja_chapter20.md":"BO0F0Kyc","ja_chapter3.md":"Ci9xkyag","ja_chapter4.md":"V6hPHOXz","ja_chapter5.md":"DtCio7E1","ja_chapter6.md":"C1cOtrBT","ja_chapter7.md":"BfRsEZoc","ja_chapter8.md":"BvdE2wRw","ja_chapter9.md":"BYhvNJ6v","ja_index.md":"DyphiH5G","ja_part1-cognition_chapter1.md":"CjelpNP-","ja_part1-cognition_chapter2.md":"ClbYJfYf","ja_part1-cognition_chapter3.md":"BfQaQGnz","ja_part2-fundamentals_chapter4.md":"C_B3HrBt","ja_part2-fundamentals_chapter5.md":"998vf9B1","ja_part2-fundamentals_chapter6.md":"DjsECIug","ja_part2-fundamentals_chapter7.md":"CgHRyPdh","ja_part3-practice_chapter10.md":"CvPivwri","ja_part3-practice_chapter11.md":"Dpr8hGOE","ja_part3-practice_chapter12.md":"Cu7bfdfo","ja_part3-practice_chapter8.md":"DpDpCRRn","ja_part3-practice_chapter9.md":"BdmeiJiF","ja_part4-advanced_chapter13.md":"BlrBPKM4","ja_part4-advanced_chapter14.md":"6aeKOz4_","ja_part4-advanced_chapter15.md":"Bi3BTUoE","ja_part5-career_chapter16.md":"DCFbmTEA","ja_part5-career_chapter17.md":"pFGKfiA8","ja_part5-career_chapter18.md":"CNyAlM_r","ja_part5-career_chapter19.md":"BLBF-Tzr","ja_part5-career_chapter20.md":"CS-nChKb","ko_appendix_appendix-a.md":"DC6BqAcc","ko_appendix_appendix-b.md":"Bdb2Ix2E","ko_appendix_appendix-c.md":"CPs2zWHP","ko_appendix_appendix-d.md":"CssLCPPg","ko_appendix_appendix-e.md":"B1Yg-Qj4","ko_chapter1.md":"ASGNpvO4","ko_chapter10.md":"C3eZ77f_","ko_chapter11.md":"CGMO9Yrh","ko_chapter12.md":"DSTOz_qU","ko_chapter13.md":"BVxA2Pwq","ko_chapter14.md":"CFJ30kg7","ko_chapter15.md":"tVZ8DnVK","ko_chapter16.md":"D7fn6DIS","ko_chapter17.md":"BnsbP3cV","ko_chapter18.md":"DCmiwPDN","ko_chapter19.md":"BWbLWnKx","ko_chapter2.md":"C5sMCplZ","ko_chapter20.md":"BoJDEG77","ko_chapter3.md":"CbcDOvb-","ko_chapter4.md":"B5jBAhox","ko_chapter5.md":"CdZhEpU3","ko_chapter6.md":"DYz7GTCL","ko_chapter7.md":"DNwlgxLN","ko_chapter8.md":"DCgJzxWV","ko_chapter9.md":"aLpcyyRR","ko_index.md":"0smLfEKM","ko_part1-cognition_chapter1.md":"BjpZAIgQ","ko_part1-cognition_chapter2.md":"8KWJ8xKO","ko_part1-cognition_chapter3.md":"BODBQiAl","ko_part2-fundamentals_chapter4.md":"Cyt9PI3S","ko_part2-fundamentals_chapter5.md":"DROtz0NT","ko_part2-fundamentals_chapter6.md":"BkXzr71g","ko_part2-fundamentals_chapter7.md":"CgmrdJTD","ko_part3-practice_chapter10.md":"B1Tb6ZeT","ko_part3-practice_chapter11.md":"Dk9MIhph","ko_part3-practice_chapter12.md":"Bh3AjecX","ko_part3-practice_chapter8.md":"xEwkGg_K","ko_part3-practice_chapter9.md":"Da2xJjz3","ko_part4-advanced_chapter13.md":"2o-nHRt0","ko_part4-advanced_chapter14.md":"B6bHyGjZ","ko_part4-advanced_chapter15.md":"BSH4p-2W","ko_part5-career_chapter16.md":"D32b6ar4","ko_part5-career_chapter17.md":"_ZvIPCOn","ko_part5-career_chapter18.md":"B4RjrOOf","ko_part5-career_chapter19.md":"sTb2O2-V","ko_part5-career_chapter20.md":"HS_Vc0R0","zh_appendix_appendix-a.md":"Cx0_82Ks","zh_appendix_appendix-b.md":"Bf5ioE4h","zh_appendix_appendix-c.md":"BU4zs0jd","zh_appendix_appendix-d.md":"Dogk2eil","zh_appendix_appendix-e.md":"DW1rt_69","zh_index.md":"D7RBfqCf","zh_part1-cognition_chapter1.md":"CcYDE_Cw","zh_part1-cognition_chapter2.md":"BMMbkHWn","zh_part1-cognition_chapter3.md":"Cd6Qk2l6","zh_part2-fundamentals_chapter4.md":"DmE715nM","zh_part2-fundamentals_chapter5.md":"OzAnH3gX","zh_part2-fundamentals_chapter6.md":"-szzT53J","zh_part2-fundamentals_chapter7.md":"d0IVfFMM","zh_part3-practice_chapter10.md":"BOLQAU7m","zh_part3-practice_chapter11.md":"CbBjjFE9","zh_part3-practice_chapter12.md":"BwmlCuM7","zh_part3-practice_chapter8.md":"BiPhaNQ-","zh_part3-practice_chapter9.md":"aRztTKaf","zh_part4-advanced_chapter13.md":"1f2Wee36","zh_part4-advanced_chapter14.md":"B7XhDIqR","zh_part4-advanced_chapter15.md":"B4oz0Ua2","zh_part5-career_chapter16.md":"CtZMXY_d","zh_part5-career_chapter17.md":"BfpkT-EM","zh_part5-career_chapter18.md":"DJMkBRQo","zh_part5-career_chapter19.md":"x4UZQlEO","zh_part5-career_chapter20.md":"CDEHG5kJ"}
